octopus_sensing_monitoring/__init__.py
octopus_sensing_monitoring/handlers.py
octopus_sensing_monitoring/main.py
octopus_sensing_monitoring-1.3.1.dist-info/METADATA
octopus_sensing_monitoring-1.3.1.dist-info/WHEEL
octopus_sensing_monitoring-1.3.1.dist-info/entry_points.txt
octopus_sensing_monitoring-1.3.1.dist-info/RECORD
