Metadata-Version: 2.3
Name: octopus-sensing-monitoring
Version: 1.3.1
Summary: Web base data monitoring/visualizer for https://octopus-sensing.nastaran-saffar.me
License: GPL-3.0-or-later
Author: Aidin Gharibnavaz
Author-email: aidin@aidinhut.com
Requires-Python: >=3.11,<4.0
Classifier: License :: OSI Approved :: GNU General Public License v3 or later (GPLv3+)
Classifier: Programming Language :: Python :: 3
Classifier: Programming Language :: Python :: 3.11
Classifier: Programming Language :: Python :: 3.12
Classifier: Programming Language :: Python :: 3.13
Requires-Dist: CherryPy (==18.10.0)
Requires-Dist: Pillow (==11.3.0)
Requires-Dist: heartpy (==1.2.7)
Requires-Dist: neurokit2 (==0.2.12)
Requires-Dist: numpy (==2.3.2)
Requires-Dist: pandas (==2.3.2)
Requires-Dist: pycairo (==1.28.0)
Project-URL: Repository, https://github.com/octopus-sensing/octopus-sensing-monitoring
